{"nodes": [{"id": "yaml_panel", "label": "yaml_panel.py", "file_type": "code", "source_file": "nav2_config/gui/yaml_panel.py", "source_location": "L1"}, {"id": "yaml_panel_yamlhighlighter", "label": "_YamlHighlighter", "file_type": "code", "source_file": "nav2_config/gui/yaml_panel.py", "source_location": "L52"}, {"id": "qsyntaxhighlighter", "label": "QSyntaxHighlighter", "file_type": "code", "source_file": "", "source_location": ""}, {"id": "yaml_panel_yamlhighlighter_init", "label": ".__init__()", "file_type": "code", "source_file": "nav2_config/gui/yaml_panel.py", "source_location": "L63"}, {"id": "yaml_panel_make_fmt", "label": "_make_fmt()", "file_type": "code", "source_file": "nav2_config/gui/yaml_panel.py", "source_location": "L70"}, {"id": "yaml_panel_yamlhighlighter_build_rules", "label": "._build_rules()", "file_type": "code", "source_file": "nav2_config/gui/yaml_panel.py", "source_location": "L77"}, {"id": "yaml_panel_yamlhighlighter_highlightblock", "label": ".highlightBlock()", "file_type": "code", "source_file": "nav2_config/gui/yaml_panel.py", "source_location": "L110"}, {"id": "yaml_panel_yamlpanel", "label": "YamlPanel", "file_type": "code", "source_file": "nav2_config/gui/yaml_panel.py", "source_location": "L125"}, {"id": "qwidget", "label": "QWidget", "file_type": "code", "source_file": "", "source_location": ""}, {"id": "yaml_panel_yamlpanel_init", "label": ".__init__()", "file_type": "code", "source_file": "nav2_config/gui/yaml_panel.py", "source_location": "L135"}, {"id": "yaml_panel_yamlpanel_build_ui", "label": "._build_ui()", "file_type": "code", "source_file": "nav2_config/gui/yaml_panel.py", "source_location": "L146"}, {"id": "yaml_panel_yamlpanel_make_title_bar", "label": "._make_title_bar()", "file_type": "code", "source_file": "nav2_config/gui/yaml_panel.py", "source_location": "L176"}, {"id": "yaml_panel_yamlpanel_update_title", "label": "._update_title()", "file_type": "code", "source_file": "nav2_config/gui/yaml_panel.py", "source_location": "L241"}, {"id": "yaml_panel_yamlpanel_copy_to_clipboard", "label": "._copy_to_clipboard()", "file_type": "code", "source_file": "nav2_config/gui/yaml_panel.py", "source_location": "L244"}, {"id": "yaml_panel_yamlpanel_extract_node_section", "label": "._extract_node_section()", "file_type": "code", "source_file": "nav2_config/gui/yaml_panel.py", "source_location": "L249"}, {"id": "yaml_panel_yamlpanel_show_filtered_yaml", "label": "._show_filtered_yaml()", "file_type": "code", "source_file": "nav2_config/gui/yaml_panel.py", "source_location": "L271"}, {"id": "yaml_panel_yamlpanel_update_yaml", "label": ".update_yaml()", "file_type": "code", "source_file": "nav2_config/gui/yaml_panel.py", "source_location": "L299"}, {"id": "yaml_panel_yamlpanel_set_current_node", "label": ".set_current_node()", "file_type": "code", "source_file": "nav2_config/gui/yaml_panel.py", "source_location": "L348"}, {"id": "yaml_panel_yamlpanel_set_file_content", "label": ".set_file_content()", "file_type": "code", "source_file": "nav2_config/gui/yaml_panel.py", "source_location": "L354"}, {"id": "yaml_panel_yamlpanel_set_save_button_dirty", "label": ".set_save_button_dirty()", "file_type": "code", "source_file": "nav2_config/gui/yaml_panel.py", "source_location": "L373"}, {"id": "yaml_panel_yamlpanel_clear_file_mode", "label": ".clear_file_mode()", "file_type": "code", "source_file": "nav2_config/gui/yaml_panel.py", "source_location": "L378"}, {"id": "yaml_panel_rationale_53", "label": "YAML syntax highlighter using VS Code Light colors.      Keys      \u2014 #0000cc  (d", "file_type": "rationale", "source_file": "nav2_config/gui/yaml_panel.py", "source_location": "L53"}, {"id": "yaml_panel_rationale_126", "label": "Right panel: YAML preview \u2014 shows file content when a config file is loaded,", "file_type": "rationale", "source_file": "nav2_config/gui/yaml_panel.py", "source_location": "L126"}, {"id": "yaml_panel_rationale_250", "label": "Extract the top-level section for *bare_node* from a full YAML string.", "file_type": "rationale", "source_file": "nav2_config/gui/yaml_panel.py", "source_location": "L250"}, {"id": "yaml_panel_rationale_272", "label": "Display only the selected node's section from *_full_yaml_str*.", "file_type": "rationale", "source_file": "nav2_config/gui/yaml_panel.py", "source_location": "L272"}, {"id": "yaml_panel_rationale_305", "label": "Regenerate the YAML preview showing only the selected node's params.          Ar", "file_type": "rationale", "source_file": "nav2_config/gui/yaml_panel.py", "source_location": "L305"}, {"id": "yaml_panel_rationale_349", "label": "Track the selected node; in file mode, re-filter the display.", "file_type": "rationale", "source_file": "nav2_config/gui/yaml_panel.py", "source_location": "L349"}, {"id": "yaml_panel_rationale_355", "label": "Store the full config file and display only the selected node's section.", "file_type": "rationale", "source_file": "nav2_config/gui/yaml_panel.py", "source_location": "L355"}, {"id": "yaml_panel_rationale_374", "label": "Enable or disable the Save button to reflect unsaved-changes state.", "file_type": "rationale", "source_file": "nav2_config/gui/yaml_panel.py", "source_location": "L374"}, {"id": "yaml_panel_rationale_379", "label": "Return to generated-YAML mode (no config file loaded).", "file_type": "rationale", "source_file": "nav2_config/gui/yaml_panel.py", "source_location": "L379"}], "edges": [{"source": "yaml_panel", "target": "logging", "relation": "imports", "confidence": "EXTRACTED", "source_file": "nav2_config/gui/yaml_panel.py", "source_location": "L12", "weight": 1.0}, {"source": "yaml_panel", "target": "re", "relation": "imports", "confidence": "EXTRACTED", "source_file": "nav2_config/gui/yaml_panel.py", "source_location": "L13", "weight": 1.0}, {"source": "yaml_panel", "target": "pyqt6_qtcore", "relation": "imports_from", "confidence": "EXTRACTED", "source_file": "nav2_config/gui/yaml_panel.py", "source_location": "L15", "weight": 1.0}, {"source": "yaml_panel", "target": "pyqt6_qtgui", "relation": "imports_from", "confidence": "EXTRACTED", "source_file": "nav2_config/gui/yaml_panel.py", "source_location": "L16", "weight": 1.0}, {"source": "yaml_panel", "target": "pyqt6_qtwidgets", "relation": "imports_from", "confidence": "EXTRACTED", "source_file": "nav2_config/gui/yaml_panel.py", "source_location": "L23", "weight": 1.0}, {"source": "yaml_panel", "target": "nav2_config_gui", "relation": "imports_from", "confidence": "EXTRACTED", "source_file": "nav2_config/gui/yaml_panel.py", "source_location": "L33", "weight": 1.0}, {"source": "yaml_panel", "target": "nav2_config_types_params", "relation": "imports_from", "confidence": "EXTRACTED", "source_file": "nav2_config/gui/yaml_panel.py", "source_location": "L35", "weight": 1.0}, {"source": "yaml_panel", "target": "nav2_config_core_yaml_exporter", "relation": "imports_from", "confidence": "EXTRACTED", "source_file": "nav2_config/gui/yaml_panel.py", "source_location": "L36", "weight": 1.0}, {"source": "yaml_panel", "target": "yaml_panel_yamlhighlighter", "relation": "contains", "confidence": "EXTRACTED", "source_file": "nav2_config/gui/yaml_panel.py", "source_location": "L52", "weight": 1.0}, {"source": "yaml_panel_yamlhighlighter", "target": "qsyntaxhighlighter", "relation": "inherits", "confidence": "EXTRACTED", "source_file": "nav2_config/gui/yaml_panel.py", "source_location": "L52", "weight": 1.0}, {"source": "yaml_panel_yamlhighlighter", "target": "yaml_panel_yamlhighlighter_init", "relation": "method", "confidence": "EXTRACTED", "source_file": "nav2_config/gui/yaml_panel.py", "source_location": "L63", "weight": 1.0}, {"source": "yaml_panel", "target": "yaml_panel_make_fmt", "relation": "contains", "confidence": "EXTRACTED", "source_file": "nav2_config/gui/yaml_panel.py", "source_location": "L70", "weight": 1.0}, {"source": "yaml_panel_yamlhighlighter", "target": "yaml_panel_yamlhighlighter_build_rules", "relation": "method", "confidence": "EXTRACTED", "source_file": "nav2_config/gui/yaml_panel.py", "source_location": "L77", "weight": 1.0}, {"source": "yaml_panel_yamlhighlighter", "target": "yaml_panel_yamlhighlighter_highlightblock", "relation": "method", "confidence": "EXTRACTED", "source_file": "nav2_config/gui/yaml_panel.py", "source_location": "L110", "weight": 1.0}, {"source": "yaml_panel", "target": "yaml_panel_yamlpanel", "relation": "contains", "confidence": "EXTRACTED", "source_file": "nav2_config/gui/yaml_panel.py", "source_location": "L125", "weight": 1.0}, {"source": "yaml_panel_yamlpanel", "target": "qwidget", "relation": "inherits", "confidence": "EXTRACTED", "source_file": "nav2_config/gui/yaml_panel.py", "source_location": "L125", "weight": 1.0}, {"source": "yaml_panel_yamlpanel", "target": "yaml_panel_yamlpanel_init", "relation": "method", "confidence": "EXTRACTED", "source_file": "nav2_config/gui/yaml_panel.py", "source_location": "L135", "weight": 1.0}, {"source": "yaml_panel_yamlpanel", "target": "yaml_panel_yamlpanel_build_ui", "relation": "method", "confidence": "EXTRACTED", "source_file": "nav2_config/gui/yaml_panel.py", "source_location": "L146", "weight": 1.0}, {"source": "yaml_panel_yamlpanel", "target": "yaml_panel_yamlpanel_make_title_bar", "relation": "method", "confidence": "EXTRACTED", "source_file": "nav2_config/gui/yaml_panel.py", "source_location": "L176", "weight": 1.0}, {"source": "yaml_panel_yamlpanel", "target": "yaml_panel_yamlpanel_update_title", "relation": "method", "confidence": "EXTRACTED", "source_file": "nav2_config/gui/yaml_panel.py", "source_location": "L241", "weight": 1.0}, {"source": "yaml_panel_yamlpanel", "target": "yaml_panel_yamlpanel_copy_to_clipboard", "relation": "method", "confidence": "EXTRACTED", "source_file": "nav2_config/gui/yaml_panel.py", "source_location": "L244", "weight": 1.0}, {"source": "yaml_panel_yamlpanel", "target": "yaml_panel_yamlpanel_extract_node_section", "relation": "method", "confidence": "EXTRACTED", "source_file": "nav2_config/gui/yaml_panel.py", "source_location": "L249", "weight": 1.0}, {"source": "yaml_panel_yamlpanel", "target": "yaml_panel_yamlpanel_show_filtered_yaml", "relation": "method", "confidence": "EXTRACTED", "source_file": "nav2_config/gui/yaml_panel.py", "source_location": "L271", "weight": 1.0}, {"source": "yaml_panel_yamlpanel", "target": "yaml_panel_yamlpanel_update_yaml", "relation": "method", "confidence": "EXTRACTED", "source_file": "nav2_config/gui/yaml_panel.py", "source_location": "L299", "weight": 1.0}, {"source": "yaml_panel_yamlpanel", "target": "yaml_panel_yamlpanel_set_current_node", "relation": "method", "confidence": "EXTRACTED", "source_file": "nav2_config/gui/yaml_panel.py", "source_location": "L348", "weight": 1.0}, {"source": "yaml_panel_yamlpanel", "target": "yaml_panel_yamlpanel_set_file_content", "relation": "method", "confidence": "EXTRACTED", "source_file": "nav2_config/gui/yaml_panel.py", "source_location": "L354", "weight": 1.0}, {"source": "yaml_panel_yamlpanel", "target": "yaml_panel_yamlpanel_set_save_button_dirty", "relation": "method", "confidence": "EXTRACTED", "source_file": "nav2_config/gui/yaml_panel.py", "source_location": "L373", "weight": 1.0}, {"source": "yaml_panel_yamlpanel", "target": "yaml_panel_yamlpanel_clear_file_mode", "relation": "method", "confidence": "EXTRACTED", "source_file": "nav2_config/gui/yaml_panel.py", "source_location": "L378", "weight": 1.0}, {"source": "yaml_panel_yamlhighlighter_init", "target": "yaml_panel_yamlpanel_init", "relation": "calls", "confidence": "EXTRACTED", "source_file": "nav2_config/gui/yaml_panel.py", "source_location": "L64", "weight": 1.0}, {"source": "yaml_panel_yamlhighlighter_init", "target": "yaml_panel_make_fmt", "relation": "calls", "confidence": "EXTRACTED", "source_file": "nav2_config/gui/yaml_panel.py", "source_location": "L66", "weight": 1.0}, {"source": "yaml_panel_yamlhighlighter_init", "target": "yaml_panel_yamlhighlighter_build_rules", "relation": "calls", "confidence": "EXTRACTED", "source_file": "nav2_config/gui/yaml_panel.py", "source_location": "L67", "weight": 1.0}, {"source": "yaml_panel_yamlhighlighter_build_rules", "target": "yaml_panel_make_fmt", "relation": "calls", "confidence": "EXTRACTED", "source_file": "nav2_config/gui/yaml_panel.py", "source_location": "L82", "weight": 1.0}, {"source": "yaml_panel_yamlpanel_init", "target": "yaml_panel_yamlpanel_build_ui", "relation": "calls", "confidence": "EXTRACTED", "source_file": "nav2_config/gui/yaml_panel.py", "source_location": "L140", "weight": 1.0}, {"source": "yaml_panel_yamlpanel_build_ui", "target": "yaml_panel_yamlpanel_make_title_bar", "relation": "calls", "confidence": "EXTRACTED", "source_file": "nav2_config/gui/yaml_panel.py", "source_location": "L151", "weight": 1.0}, {"source": "yaml_panel_yamlpanel_build_ui", "target": "yaml_panel_yamlhighlighter", "relation": "calls", "confidence": "EXTRACTED", "source_file": "nav2_config/gui/yaml_panel.py", "source_location": "L171", "weight": 1.0}, {"source": "yaml_panel_yamlpanel_build_ui", "target": "yaml_panel_yamlpanel_update_title", "relation": "calls", "confidence": "EXTRACTED", "source_file": "nav2_config/gui/yaml_panel.py", "source_location": "L174", "weight": 1.0}, {"source": "yaml_panel_yamlpanel_make_title_bar", "target": "qwidget", "relation": "calls", "confidence": "EXTRACTED", "source_file": "nav2_config/gui/yaml_panel.py", "source_location": "L177", "weight": 1.0}, {"source": "yaml_panel_yamlpanel_show_filtered_yaml", "target": "yaml_panel_yamlpanel_update_title", "relation": "calls", "confidence": "EXTRACTED", "source_file": "nav2_config/gui/yaml_panel.py", "source_location": "L275", "weight": 1.0}, {"source": "yaml_panel_yamlpanel_show_filtered_yaml", "target": "yaml_panel_yamlpanel_extract_node_section", "relation": "calls", "confidence": "EXTRACTED", "source_file": "nav2_config/gui/yaml_panel.py", "source_location": "L279", "weight": 1.0}, {"source": "yaml_panel_yamlpanel_update_yaml", "target": "yaml_panel_yamlpanel_update_title", "relation": "calls", "confidence": "EXTRACTED", "source_file": "nav2_config/gui/yaml_panel.py", "source_location": "L318", "weight": 1.0}, {"source": "yaml_panel_yamlpanel_set_current_node", "target": "yaml_panel_yamlpanel_show_filtered_yaml", "relation": "calls", "confidence": "EXTRACTED", "source_file": "nav2_config/gui/yaml_panel.py", "source_location": "L352", "weight": 1.0}, {"source": "yaml_panel_yamlpanel_set_file_content", "target": "yaml_panel_yamlpanel_show_filtered_yaml", "relation": "calls", "confidence": "EXTRACTED", "source_file": "nav2_config/gui/yaml_panel.py", "source_location": "L371", "weight": 1.0}, {"source": "yaml_panel_yamlpanel_clear_file_mode", "target": "yaml_panel_yamlpanel_update_title", "relation": "calls", "confidence": "EXTRACTED", "source_file": "nav2_config/gui/yaml_panel.py", "source_location": "L384", "weight": 1.0}, {"source": "yaml_panel_rationale_53", "target": "yaml_panel_yamlhighlighter", "relation": "rationale_for", "confidence": "EXTRACTED", "source_file": "nav2_config/gui/yaml_panel.py", "source_location": "L53", "weight": 1.0}, {"source": "yaml_panel_rationale_126", "target": "yaml_panel_yamlpanel", "relation": "rationale_for", "confidence": "EXTRACTED", "source_file": "nav2_config/gui/yaml_panel.py", "source_location": "L126", "weight": 1.0}, {"source": "yaml_panel_rationale_250", "target": "yaml_panel_yamlpanel_extract_node_section", "relation": "rationale_for", "confidence": "EXTRACTED", "source_file": "nav2_config/gui/yaml_panel.py", "source_location": "L250", "weight": 1.0}, {"source": "yaml_panel_rationale_272", "target": "yaml_panel_yamlpanel_show_filtered_yaml", "relation": "rationale_for", "confidence": "EXTRACTED", "source_file": "nav2_config/gui/yaml_panel.py", "source_location": "L272", "weight": 1.0}, {"source": "yaml_panel_rationale_305", "target": "yaml_panel_yamlpanel_update_yaml", "relation": "rationale_for", "confidence": "EXTRACTED", "source_file": "nav2_config/gui/yaml_panel.py", "source_location": "L305", "weight": 1.0}, {"source": "yaml_panel_rationale_349", "target": "yaml_panel_yamlpanel_set_current_node", "relation": "rationale_for", "confidence": "EXTRACTED", "source_file": "nav2_config/gui/yaml_panel.py", "source_location": "L349", "weight": 1.0}, {"source": "yaml_panel_rationale_355", "target": "yaml_panel_yamlpanel_set_file_content", "relation": "rationale_for", "confidence": "EXTRACTED", "source_file": "nav2_config/gui/yaml_panel.py", "source_location": "L355", "weight": 1.0}, {"source": "yaml_panel_rationale_374", "target": "yaml_panel_yamlpanel_set_save_button_dirty", "relation": "rationale_for", "confidence": "EXTRACTED", "source_file": "nav2_config/gui/yaml_panel.py", "source_location": "L374", "weight": 1.0}, {"source": "yaml_panel_rationale_379", "target": "yaml_panel_yamlpanel_clear_file_mode", "relation": "rationale_for", "confidence": "EXTRACTED", "source_file": "nav2_config/gui/yaml_panel.py", "source_location": "L379", "weight": 1.0}]}